github_downloader/__init__.py
github_downloader/cli.py
github_downloader/constants.py
github_downloader/download.py
github_downloader/lib.py
github_downloader/logging.py
github_downloader/py.typed
github_downloader/settings.py
github_downloader/types.py
github_downloader/utilities.py
dycw_github_downloader-0.1.27.dist-info/WHEEL
dycw_github_downloader-0.1.27.dist-info/entry_points.txt
dycw_github_downloader-0.1.27.dist-info/METADATA
dycw_github_downloader-0.1.27.dist-info/RECORD
