Metadata-Version: 2.3
Name: dycw-github-downloader
Version: 0.1.27
Summary: GitHub release downloader
Author: Derek Wan
Author-email: Derek Wan <d.wan@icloud.com>
Requires-Dist: click>=8.3.1,<9
Requires-Dist: dycw-utilities>=0.179.1,<1
Requires-Dist: inflect>=7.5.0,<8
Requires-Dist: pygithub>=2.8.1,<3
Requires-Dist: rich>=14.2.0,<15
Requires-Dist: typed-settings[attrs,click]>=25.3.0,<26
Requires-Python: >=3.12
